Metadata-Version: 2.1
Name: dark_image_processing
Version: 0.0.1
Summary: Processamento de Imagens com Python
Home-page: https://github.com/DarkSoulBr/image-processing-package
Author: Luis Ramires
Author-email: luis.ramires@uol.com.br
Requires-Python: >=3.8
Requires-Dist: matplotlib
Requires-Dist: scikit-image
